{"informacoesCota":{"codigoGrupo":"001830","codigoCota":434,"versao":0,"prazoVenda":216,"nomeBem":"CRÉDITO DE IMÓVEL 750.000,00","valorAtualBem":750000.00,"prazoComercializacao":216},"disponibilidade":{"dataReferencia":"2022-12-01T00:00:00","dataReferenciaAtual":"2022-12-31T00:00:00","dataReferenciaAnterior":"2022-11-30T00:00:00","valorDisponibilidadeAnterior":20264747.86,"valorDisponibilidadeAnteriorAcumulado":0,"valorDispAnteriorCaixa":0.00,"valorDispAnteriorDepositoBancarios":88898.08,"valorDispAnteriorChequeCob":0.00,"valorDispAnteriorAplicacaoFinGrupo":1184273.34,"valorDispAnteriorAplicacaoVincContemp":18991576.44,"valorDispAnteriorCaixaAcumulado":0,"valorDispAnteriorDepositoBancariosAcumulado":0,"valorDispAnteriorChequeCobAcumulado":0,"valorDispAnteriorAplicacaoFinGrupoAcumulado":0,"valorRecursosColetados":3569683.26,"valorRecursosColetadosAcumulados":61501690.31,"valorDispAnteriorAplicacaoVincContempAcumulado":0,"valorRecColContribuicoesAquBem":2380298.51,"valorRecColTaxaAdm":924000.57,"valorRecColContribFundoReserva":0.00,"valorRecColRendimentoAplicFin":155846.89,"valorRecColMultaJuros":4373.13,"valorRecColPremioSeguro":93316.75,"valorRecColCustasJudiciais":10518.00,"valorRecColReembolsoDespesas":0.00,"valorRecColOutros":1329.41,"valorRecColContribuicoesAquBemAcumulado":34773896.72,"valorRecColTaxaAdmAcumulado":22732999.65,"valorRecColContribFundoReservaAcumulado":0.00,"valorRecColRendimentoAplicFinAcumulado":1749301.69,"valorRecColMultaJurosAcumulado":75177.30,"valorRecColPremioSeguroAcumulado":1999034.14,"valorRecColCustasJudiciaisAcumulado":159995.97,"valorRecColReembolsoDespesasAcumulado":0.00,"valorRecColOutrosAcumulado":11284.84,"valorRecursosUtilizados":5065984.07,"valorRecursosUtilizadosAcumulado":42733243.26,"valorRecUtAquisicaoBens":3341597.04,"valorRecUtTaxaAdm":1600316.84,"valorRecUtMultaJuros":2186.57,"valorRecUtPremiosSeguro":112212.80,"valorRecUtCustasJudiciais":7012.00,"valorRecUtDevolucaoDesligados":0.00,"valorRecUtDespesasRegistroContra":0.00,"valorRecUtOutros":2658.82,"valorRecUtAquisicaoBensAcumulado":23427590.89,"valorRecUtTaxaAdmAcumulado":17173607.81,"valorRecUtMultaJurosAcumulado":37386.54,"valorRecUtPremiosSeguroAcumulado":1905717.39,"valorRecUtCustasJudiciaisAcumulado":155839.97,"valorRecUtDevolucaoDesligadosAcumulado":10530.98,"valorRecUtDespesasRegistroContraAcumulado":0.00,"valorRecUtOutrosAcumulado":22569.68,"valorDisponilidadeAtual":18768447.05,"valorDisponilidadeAtualAcumulado":18768447.05,"valorDispAtualCaixa":0.00,"valorDispAtualDepositoBancarios":104170.53,"valorDispAtualAplicacaoFin":0.00,"valorDispAtualChequeCob":0.00,"valorDispAtualAplicacaoFinGrupo":762387.09,"valorDispAtualAplicacaoVincContemp":17901889.43,"valorDispAtualCaixaAcumulado":0.00,"valorDispAtualDepositoBancariosAcumulado":104170.53,"valorDispAtualAplicacaoFinAcumulado":0.00,"valorDispAtualChequeCobAcumulado":0.00,"valorDispAtualAplicacaoFinGrupoAcumulado":762387.09,"valorDispAtualAplicacaoVincContempAcumulado":17901889.43,"quantidadeCotasBensEntregues":26,"quantidadeCotasBensEntregar":44,"quantidadeCotasNaoContempladas":573,"quantidadeCotasAtivas":643,"quantidadeCotasDesistentes":889,"quantidadeCotasQuitadas":2,"quantidadeCotasContempladas":70,"valorDispAnteriorAplicacoesFinanceiras":0.00,"valorDispAnteriorAplicacoesFinanceirasAcumulado":0,"valorRecUtRendimentosPagosCont":0.00,"valorRecUtRendimentosPagosContAcumulado":0.00,"valorBemEntregar":17901889.00,"valorBemEntregarAcumulado":17901889.00},"informacoesGrupoAssembleia":{"numeroAssembleia":29,"dataAssembleia":"2023-02-14T00:00:00","dataVencimento":"2023-02-10T00:00:00","dataSorteio":"2023-02-14T00:00:00","horaAssembleia":"17:30","numeroAssembleiaDemonstrativoAtualizado":48},"proximaAssembleia":{"noProximaAssembleia":30,"dataProximaAssembleia":"2023-03-14T00:00:00","horaProximaAssembleia":"17:30","nomeProximoLocal":"RODOBENS COMUNICACAO EMPRESARIAL LTDA   ","nomeProximoEndereco":"AV MURCHID HOMSI, 01404"},"assembleiaAnterior":{"numeroAssembleiaAnterior":28,"dataAssembleiaAnterior":"2023-01-12T00:00:00","demonstrativoAnterior":true},"contempladosLanceAssembleiaAnterior":[{"codigoCota":119,"versao":0,"numeroAssembleia":28,"dataAssembleia":"2023-01-12T00:00:00","percentualLance":89.4825,"situacaoModalidade":"Lance Livre","numeroSequencia":4,"vaLance":"131","criterioOferta":"Parcelas"},{"codigoCota":92,"versao":0,"numeroAssembleia":28,"dataAssembleia":"2023-01-12T00:00:00","percentualLance":33.5249,"situacaoModalidade":"Lance Fixo","numeroSequencia":2,"vaLance":"065","criterioOferta":"Parcelas"},{"codigoCota":214,"versao":0,"numeroAssembleia":28,"dataAssembleia":"2023-01-12T00:00:00","percentualLance":112.2026,"situacaoModalidade":"Lance Livre","numeroSequencia":3,"vaLance":"134","criterioOferta":"Parcelas"}],"contempladosSorteioAssembleiaAnterior":[{"codigoCota":88,"versao":0,"numeroAssembleia":28,"dataAssembleia":"2023-01-12T00:00:00","numeroSequencia":1}],"proximaParcela":{"numeroIdentificador":null,"dataInclusao":null,"numeroParcela":null,"dataVencimento":null,"percentualAmortizacao":null,"percentualAmortizar":null},"decomposicaoMensalidade":{"valorFundoComum":null,"valorFundoReserva":null,"valorSeguro":null,"valorTaxaAdministracao":null,"valorDiferenca":null,"valorMultaJuros":null,"valorTotal":null,"percentualFundoComum":null,"percentualFundoReserva":null,"percentualFundoReservaPlano":0.0000,"percentualSeguro":null,"percentualTaxaAdministracao":null,"percentualTaxaAdministracaoPlano":24.0000,"percentualDiferenca":null,"percentualMultaJuros":null,"percentualTotal":null,"percentualReajusteSaldo":null,"valorReajusteSaldo":null},"extratoContaCorrente":[]}